openapi2oms/Converter.py
openapi2oms/Properties.py
openapi2oms/Service.py
openapi2oms/__init__.py
openapi2oms/exceptions/ConverterError.py
openapi2oms/exceptions/MappingError.py
openapi2oms/exceptions/__init__.py
openapi2oms/utils/OpenAPIActionUtil.py
openapi2oms/utils/__init__.py
openapi2oms-0.1.0.dist-info/LICENSE
openapi2oms-0.1.0.dist-info/METADATA
openapi2oms-0.1.0.dist-info/WHEEL
openapi2oms-0.1.0.dist-info/top_level.txt
openapi2oms-0.1.0.dist-info/RECORD
